RMtools_1D/__init__.py
RMtools_1D/calculate_RMSF.py
RMtools_1D/clean_model.py
RMtools_1D/do_QUfit_1D_mnest.py
RMtools_1D/do_RMclean_1D.py
RMtools_1D/do_RMsynth_1D.py
RMtools_1D/do_RMsynth_1D_fromFITS.py
RMtools_1D/mk_test_ascii_data.py
RMtools_1D/rmtools_bwdepol.py
RMtools_1D/rmtools_bwpredict.py
RMtools_1D/cats/catComplex.csv
RMtools_1D/cats/cat_simple_doQUfit.bat
RMtools_1D/cats/catalogue.csv
RMtools_1D/cats/catalogue1.csv
RMtools_1D/cats/testCat.dat
RMtools_1D/models_ns/__init__.py
RMtools_1D/models_ns/m1.py
RMtools_1D/models_ns/m11.py
RMtools_1D/models_ns/m111.py
RMtools_1D/models_ns/m12.py
RMtools_1D/models_ns/m2.py
RMtools_1D/models_ns/m3.py
RMtools_1D/models_ns/m4.py
RMtools_1D/models_ns/m5.py
RMtools_1D/models_ns/m6.py
RMtools_1D/models_ns/m7.py
RMtools_3D/RMpeakfit_3D.py
RMtools_3D/__init__.py
RMtools_3D/assemble_chunks.py
RMtools_3D/create_chunks.py
RMtools_3D/do_RMclean_3D.py
RMtools_3D/do_RMsynth_3D.py
RMtools_3D/do_fitIcube.py
RMtools_3D/extract_region.py
RMtools_3D/make_freq_file.py
RMtools_3D/mk_test_cube_data.py
RMtools_3D/rescale_I_model_3D.py
RMutils/__init__.py
RMutils/mpfit.py
RMutils/normalize.py
RMutils/util_FITS.py
RMutils/util_RM.py
RMutils/util_misc.py
RMutils/util_plotFITS.py
RMutils/util_plotTk.py
RMutils/util_rec.py
RMutils/util_testing.py
rm_tools-1.4.10.dist-info/licenses/LICENSE.txt
rm_tools-1.4.10.dist-info/METADATA
rm_tools-1.4.10.dist-info/WHEEL
rm_tools-1.4.10.dist-info/entry_points.txt
rm_tools-1.4.10.dist-info/top_level.txt
rm_tools-1.4.10.dist-info/RECORD
