Metadata-Version: 2.4
Name: RM-Tools
Version: 1.4.10
Summary: RM-synthesis, RM-clean and QU-fitting on polarised radio spectra
Home-page: https://github.com/CIRADA-Tools/RM-Tools
Download-URL: https://github.com/CIRADA-Tools/RM-Tools/archive/v1.4.10.tar.gz
Maintainer: Cameron Van Eck
Maintainer-email: cameron.vaneck@anu.edu.au
License: MIT
Classifier: Development Status :: 5 - Production/Stable
Classifier: License :: OSI Approved :: MIT License
Classifier: Programming Language :: Python
Classifier: Programming Language :: Python :: 3
Classifier: Programming Language :: Python :: 3.7
Classifier: Intended Audience :: Science/Research
Classifier: Topic :: Scientific/Engineering :: Astronomy
Requires-Python: >=3.8.0
License-File: LICENSE.txt
Requires-Dist: numpy<2
Requires-Dist: numpy>1.22; python_version == "3.8"
Requires-Dist: scipy
Requires-Dist: matplotlib>=3.4.0
Requires-Dist: astropy
Requires-Dist: tdqm
Requires-Dist: deprecation
Requires-Dist: finufft
Provides-Extra: qufitting
Requires-Dist: bilby>=1.1.5; extra == "qufitting"
Requires-Dist: emcee; extra == "qufitting"
Requires-Dist: nestle; extra == "qufitting"
Requires-Dist: corner; extra == "qufitting"
Provides-Extra: parallel
Requires-Dist: schwimmbad; extra == "parallel"
Provides-Extra: dev
Requires-Dist: pre-commit; extra == "dev"
Requires-Dist: black; extra == "dev"
Requires-Dist: isort; extra == "dev"
Requires-Dist: pytest; extra == "dev"
Dynamic: classifier
Dynamic: description
Dynamic: description-content-type
Dynamic: download-url
Dynamic: home-page
Dynamic: license
Dynamic: license-file
Dynamic: maintainer
Dynamic: maintainer-email
Dynamic: provides-extra
Dynamic: requires-dist
Dynamic: requires-python
Dynamic: summary
